docuquery_ai/__init__.py
docuquery_ai/client.py
docuquery_ai/cli/__init__.py
docuquery_ai/cli/main.py
docuquery_ai/core/__init__.py
docuquery_ai/core/config.py
docuquery_ai/core/database.py
docuquery_ai/core/database_migration.py
docuquery_ai/core/database_seed.py
docuquery_ai/core/security.py
docuquery_ai/models/__init__.py
docuquery_ai/models/db_models.py
docuquery_ai/models/pydantic_models.py
docuquery_ai/models/user.py
docuquery_ai/services/__init__.py
docuquery_ai/services/data_handler.py
docuquery_ai/services/file_parser.py
docuquery_ai/services/file_service.py
docuquery_ai/services/google_auth_service.py
docuquery_ai/services/nlp_service.py
docuquery_ai/services/query_engine.py
docuquery_ai/services/user_service.py
docuquery_ai/services/vector_store.py
docuquery_ai-0.1.1.dist-info/licenses/LICENSE
docuquery_ai-0.1.1.dist-info/METADATA
docuquery_ai-0.1.1.dist-info/WHEEL
docuquery_ai-0.1.1.dist-info/entry_points.txt
docuquery_ai-0.1.1.dist-info/top_level.txt
docuquery_ai-0.1.1.dist-info/RECORD
