Metadata-Version: 2.4
Name: docuquery-ai
Version: 0.1.1
Summary: A powerful document query system using RAG and LLM technologies
Author-email: DocuQuery AI Team <contact@docuquery-ai.com>
Maintainer-email: DocuQuery AI Team <contact@docuquery-ai.com>
License: MIT
Project-URL: Homepage, https://github.com/saichowdary007/docu-query
Project-URL: Documentation, https://github.com/saichowdary007/docu-query/blob/main/README.md
Project-URL: Repository, https://github.com/saichowdary007/docu-query.git
Project-URL: Issues, https://github.com/saichowdary007/docu-query/issues
Project-URL: Changelog, https://github.com/saichowdary007/docu-query/blob/main/CHANGELOG.md
Keywords: ai,llm,rag,document-processing,nlp,vector-search,langchain,google-vertex-ai,pdf-parser,machine-learning
Classifier: Development Status :: 4 - Beta
Classifier: Intended Audience :: Developers
Classifier: Intended Audience :: Science/Research
Classifier: Operating System :: OS Independent
Classifier: Programming Language :: Python :: 3
Classifier: Programming Language :: Python :: 3.8
Classifier: Programming Language :: Python :: 3.9
Classifier: Programming Language :: Python :: 3.10
Classifier: Programming Language :: Python :: 3.11
Classifier: Topic :: Scientific/Engineering :: Artificial Intelligence
Classifier: Topic :: Software Development :: Libraries :: Python Modules
Classifier: Topic :: Text Processing :: Linguistic
Requires-Python: >=3.8
License-File: LICENSE
Requires-Dist: fastapi>=0.100.0
Requires-Dist: pydantic>=2.0.0
Requires-Dist: pydantic-settings>=2.0.0
Requires-Dist: langchain>=0.1.0
Requires-Dist: langchain-community>=0.0.10
Requires-Dist: langchain-google-vertexai>=0.1.0
Requires-Dist: langchain-text-splitters>=0.0.1
Requires-Dist: google-cloud-aiplatform>=1.38.0
Requires-Dist: faiss-cpu>=1.7.4
Requires-Dist: pandas>=1.5.0
Requires-Dist: xlrd>=2.0.1
Requires-Dist: openpyxl>=3.1.0
Requires-Dist: python-docx>=0.8.11
Requires-Dist: python-pptx>=0.6.21
Requires-Dist: pypdf>=3.15.0
Requires-Dist: markdown>=3.4.0
Requires-Dist: requests>=2.28.0
Requires-Dist: python-dotenv>=1.0.0
Requires-Dist: numpy>=1.24.0
Requires-Dist: python-jose[cryptography]>=3.3.0
Requires-Dist: passlib[bcrypt]>=1.7.4
Requires-Dist: bcrypt>=4.0.0
Requires-Dist: email-validator>=2.0.0
Requires-Dist: sqlalchemy>=2.0.0
Requires-Dist: click>=8.0.0
Provides-Extra: dev
Requires-Dist: pytest>=7.0.0; extra == "dev"
Requires-Dist: pytest-asyncio>=0.21.0; extra == "dev"
Requires-Dist: pytest-cov>=4.0.0; extra == "dev"
Requires-Dist: black==23.12.1; extra == "dev"
Requires-Dist: isort==5.12.0; extra == "dev"
Requires-Dist: flake8>=6.0.0; extra == "dev"
Requires-Dist: mypy==1.6.1; extra == "dev"
Requires-Dist: pre-commit>=3.0.0; extra == "dev"
Requires-Dist: types-requests>=2.31.0.20240417; extra == "dev"
Requires-Dist: types-Markdown>=3.5.0.20240215; extra == "dev"
Provides-Extra: web
Requires-Dist: uvicorn[standard]>=0.23.0; extra == "web"
Requires-Dist: gunicorn>=21.0.0; extra == "web"
Requires-Dist: python-multipart>=0.0.6; extra == "web"
Provides-Extra: gpu
Requires-Dist: faiss-gpu>=1.7.4; extra == "gpu"
Dynamic: license-file
